OpenAIAuth.py
OpenAIAuth-3.0.0.dist-info/LICENSE
OpenAIAuth-3.0.0.dist-info/METADATA
OpenAIAuth-3.0.0.dist-info/WHEEL
OpenAIAuth-3.0.0.dist-info/top_level.txt
OpenAIAuth-3.0.0.dist-info/RECORD
