Metadata-Version: 2.1
Name: OpenAIAuth
Version: 3.0.0
Summary: OpenAI Authentication Reverse Engineered
Home-page: https://github.com/acheong08/OpenAIAuth
Author: pengzhile
Author-email: acheong@student.dalat.org
License: MIT
Project-URL: Bug Report, https://github.com/acheong08/OpenAIAuth/issues/new
Classifier: License :: OSI Approved :: MIT License
Classifier: Intended Audience :: Developers
Classifier: Natural Language :: English
Classifier: Topic :: Software Development :: Libraries :: Python Modules
Classifier: Programming Language :: Python :: 3 :: Only
Classifier: Programming Language :: Python :: 3.7
Classifier: Programming Language :: Python :: 3.8
Classifier: Programming Language :: Python :: 3.9
Classifier: Programming Language :: Python :: 3.10
Classifier: Programming Language :: Python :: 3.11
License-File: LICENSE
